tgEasy/__init__.py
tgEasy/config.py
tgEasy/scaffold.py
tgEasy/decorater/__init__.py
tgEasy/decorater/adminsOnly.py
tgEasy/decorater/callback.py
tgEasy/decorater/command.py
tgEasy/helpers/__init__.py
tgEasy/helpers/admin_utils.py
tgEasy/helpers/get_user.py
tgEasy/helpers/handle_error.py
tgEasy/helpers/send_typing.py
tgEasy-1.3.3.dist-info/LICENSE
tgEasy-1.3.3.dist-info/METADATA
tgEasy-1.3.3.dist-info/NOTICE
tgEasy-1.3.3.dist-info/WHEEL
tgEasy-1.3.3.dist-info/top_level.txt
tgEasy-1.3.3.dist-info/RECORD
