Metadata-Version: 2.1
Name: tgEasy
Version: 1.3.3
Summary: Easy for a brighter Shine, A Monkey Patcher add-on for Pyrogram
Home-page: https://github.com/jayantkageri/tgEasy
Download-URL: https://github.com/jayantkageri/tgEasy/releases/latest
Author: Jayant Hegde Kageri
Author-email: jayantkageri@gmail.com
License: LGPLv3+
Project-URL: Tracker, https://github.com/jayantkageri/tgEasys/issues
Project-URL: Community, https://telegram.me/tgEasyNews
Project-URL: Source, https://github.com/jayantkageri/tgEasy
Project-URL: Documentation, https://github.com/jayantkageri/tgEasy#documatation
Keywords: telegram chat messenger mtproto api client library python pyrogram tgeasy
Platform: UNKNOWN
Classifier: Development Status :: 5 - Production/Stable
Classifier: Intended Audience :: Developers
Classifier: Natural Language :: English
Classifier: License :: OSI Approved :: GNU Lesser General Public License v3 or later (LGPLv3+)
Classifier: Operating System :: OS Independent
Classifier: Programming Language :: Python
Classifier: Programming Language :: Python :: 3
Classifier: Programming Language :: Python :: 3.6
Classifier: Programming Language :: Python :: 3.7
Classifier: Programming Language :: Python :: 3.8
Classifier: Programming Language :: Python :: 3.9
Classifier: Programming Language :: Python :: Implementation
Classifier: Programming Language :: Python :: Implementation :: CPython
Classifier: Programming Language :: Python :: Implementation :: PyPy
Classifier: Topic :: Internet
Classifier: Topic :: Communications
Classifier: Topic :: Communications :: Chat
Classifier: Topic :: Software Development :: Libraries
Classifier: Topic :: Software Development :: Libraries :: Python Modules
Requires-Python: ~=3.6
License-File: LICENSE
License-File: NOTICE
Requires-Dist: pyrogram
Requires-Dist: TgCrypto
Requires-Dist: pyromod
Requires-Dist: prettyconf
Requires-Dist: cachetools
